odoo/addons/stock_picking_purchase_order_link/README.rst
odoo/addons/stock_picking_purchase_order_link/__init__.py
odoo/addons/stock_picking_purchase_order_link/__manifest__.py
odoo/addons/stock_picking_purchase_order_link/i18n/es.po
odoo/addons/stock_picking_purchase_order_link/i18n/fr.po
odoo/addons/stock_picking_purchase_order_link/i18n/it.po
odoo/addons/stock_picking_purchase_order_link/i18n/pt_BR.po
odoo/addons/stock_picking_purchase_order_link/i18n/stock_picking_purchase_order_link.pot
odoo/addons/stock_picking_purchase_order_link/readme/CONTRIBUTORS.md
odoo/addons/stock_picking_purchase_order_link/readme/DESCRIPTION.md
odoo/addons/stock_picking_purchase_order_link/readme/USAGE.md
odoo/addons/stock_picking_purchase_order_link/static/description/icon.png
odoo/addons/stock_picking_purchase_order_link/static/description/index.html
odoo/addons/stock_picking_purchase_order_link/views/stock_picking_view.xml
odoo_addon_stock_picking_purchase_order_link-18.0.1.0.0.3.dist-info/METADATA
odoo_addon_stock_picking_purchase_order_link-18.0.1.0.0.3.dist-info/WHEEL
odoo_addon_stock_picking_purchase_order_link-18.0.1.0.0.3.dist-info/top_level.txt
odoo_addon_stock_picking_purchase_order_link-18.0.1.0.0.3.dist-info/RECORD
