Metadata-Version: 2.1
Name: odoo-addon-stock_picking_purchase_order_link
Version: 18.0.1.0.0.3
Requires-Python: >=3.10
Requires-Dist: odoo==18.0.*
Summary: Link between picking and purchase order
Home-page: https://github.com/OCA/stock-logistics-workflow
License: AGPL-3
Author: ForgeFlow S.L., Odoo Community Association (OCA)
Author-email: support@odoo-community.org
Classifier: Programming Language :: Python
Classifier: Framework :: Odoo
Classifier: Framework :: Odoo :: 18.0
Classifier: License :: OSI Approved :: GNU Affero General Public License v3
